qkit/__init__.py
qkit/spectroscopy.py
qkit/analysis/CurveXtractor.py
qkit/analysis/IV_curve.py
qkit/analysis/IV_curve2.py
qkit/analysis/IV_curve3.py
qkit/analysis/__init__.py
qkit/analysis/avoided_crossing_fit.py
qkit/analysis/iq_cloud_analysis.py
qkit/analysis/manual_point_picker.py
qkit/analysis/pointtracker.py
qkit/analysis/qfit.py
qkit/analysis/qps_rings.py
qkit/analysis/resonator.py
qkit/analysis/circle_fit/__init__.py
qkit/analysis/circle_fit/circle_fit_2019/__init__.py
qkit/analysis/circle_fit/circle_fit_2019/circuit.py
qkit/analysis/circle_fit/circle_fit_advanced/__init__.py
qkit/analysis/circle_fit/circle_fit_advanced/circle_fitter.py
qkit/analysis/circle_fit/circle_fit_advanced/circuit.py
qkit/analysis/circle_fit/circle_fit_advanced/fitted_resonator.py
qkit/analysis/circle_fit/circle_fit_advanced/helper_functions.py
qkit/analysis/circle_fit/circle_fit_advanced/resonator.py
qkit/analysis/circle_fit/circle_fit_classic/__init__.py
qkit/analysis/circle_fit/circle_fit_classic/calibration.py
qkit/analysis/circle_fit/circle_fit_classic/circlefit.py
qkit/analysis/circle_fit/circle_fit_classic/circuit.py
qkit/analysis/circle_fit/circle_fit_classic/utilities.py
qkit/analysis/circle_fit/circle_fit_tanmay/__init__.py
qkit/analysis/circle_fit/circle_fit_tanmay/circuit.py
qkit/config/__init__.py
qkit/config/environment.py
qkit/core/__init__.py
qkit/core/flow.py
qkit/core/instrument_base.py
qkit/core/instrument_basev2.py
qkit/core/instrument_tools.py
qkit/core/startup.py
qkit/core/lib/__init__.py
qkit/core/lib/list_dict_DB.py
qkit/core/lib/misc.py
qkit/core/lib/temp.py
qkit/core/lib/com/__init__.py
qkit/core/lib/com/info_client.py
qkit/core/lib/com/info_service.py
qkit/core/lib/com/ri_client.py
qkit/core/lib/com/ri_service.py
qkit/core/lib/com/signals.py
qkit/core/lib/file_service/__init__.py
qkit/core/lib/file_service/file_info_database.py
qkit/core/lib/file_service/file_info_database_lib.py
qkit/core/lib/network/__init__.py
qkit/core/lib/network/tcpclient.py
qkit_gla-0.0.1rc0.dist-info/licenses/AUTHORS
qkit_gla-0.0.1rc0.dist-info/licenses/LICENSE
qkit_gla-0.0.1rc0.dist-info/METADATA
qkit_gla-0.0.1rc0.dist-info/WHEEL
qkit_gla-0.0.1rc0.dist-info/entry_points.txt
qkit_gla-0.0.1rc0.dist-info/top_level.txt
qkit_gla-0.0.1rc0.dist-info/RECORD
