Metadata-Version: 2.4
Name: qkit-gla
Version: 0.0.1rc0
Summary: A quantum measurement toolkit for superconducting qubits and resonators
Author-email: Wridhdhisom Karar <w.karar.1@research.gla.ac.uk>
Maintainer-email: Quantum Circuits Group Glasgow <eng-weideslab@gla.ac.uk>
License:                     GNU GENERAL PUBLIC LICENSE
Project-URL: Homepage, https://github.com/qkitgroup/qkit
Project-URL: Documentation, https://qkit.readthedocs.io
Project-URL: Repository, https://github.com/qkitgroup/qkit
Project-URL: Issues, https://github.com/qkitgroup/qkit/issues
Keywords: physics,quantum,measurement,superconducting,resonator
Classifier: Development Status :: 4 - Beta
Classifier: Intended Audience :: Science/Research
Classifier: License :: OSI Approved :: MIT License
Classifier: Operating System :: OS Independent
Classifier: Programming Language :: Python
Classifier: Programming Language :: Python :: 3
Classifier: Programming Language :: Python :: 3.9
Classifier: Programming Language :: Python :: 3.10
Classifier: Programming Language :: Python :: 3.11
Classifier: Programming Language :: Python :: 3.12
Classifier: Topic :: Scientific/Engineering :: Physics
Classifier: Topic :: Software Development :: Libraries :: Python Modules
Requires-Python: >=3.9
License-File: LICENSE
License-File: AUTHORS
Requires-Dist: ipython>=8.12.3
Requires-Dist: setuptools>=75.8.0
Requires-Dist: h5py==3.8.0
Requires-Dist: pyqt5==5.15.9
Requires-Dist: pyqtgraph==0.13.3
Requires-Dist: PyVISA==1.13.0
Requires-Dist: PyVISA-py==0.6.3
Requires-Dist: zhinst==23.2.4
Requires-Dist: pyzmq==25.0.2
Requires-Dist: numpy==1.24.2
Requires-Dist: scipy==1.10.1
Requires-Dist: jupyterlab==3.6.3
Requires-Dist: jupyterlab-templates==0.4.0
Requires-Dist: ipywidgets==8.0.6
Requires-Dist: matplotlib==3.7.1
Requires-Dist: uncertainties==3.1.7
Provides-Extra: dev
Requires-Dist: pytest>=7.0.0; extra == "dev"
Requires-Dist: pytest-cov>=4.0.0; extra == "dev"
Requires-Dist: black>=23.0.0; extra == "dev"
Requires-Dist: isort>=5.0.0; extra == "dev"
Requires-Dist: ruff>=0.1.0; extra == "dev"
Requires-Dist: mypy>=1.0.0; extra == "dev"
Requires-Dist: autoflake>=2.0.0; extra == "dev"
Requires-Dist: pyupgrade>=3.0.0; extra == "dev"
Requires-Dist: vulture>=2.0.0; extra == "dev"
Requires-Dist: pre-commit>=3.0.0; extra == "dev"
Requires-Dist: pip-tools>=7.0.0; extra == "dev"
Provides-Extra: test
Requires-Dist: pytest>=7.0.0; extra == "test"
Requires-Dist: pytest-cov>=4.0.0; extra == "test"
Requires-Dist: pytest-mock>=3.0.0; extra == "test"
Provides-Extra: docs
Requires-Dist: sphinx>=5.0.0; extra == "docs"
Requires-Dist: sphinx-rtd-theme>=1.0.0; extra == "docs"
Requires-Dist: myst-parser>=0.18.0; extra == "docs"
Provides-Extra: all
Requires-Dist: qkit[dev,docs,test]; extra == "all"
Dynamic: license-file
